CHANGES.txt
CONTRIBUTORS.txt
README.rst
bootstrap.py
buildout.cfg
setup.cfg
setup.py
docs/LICENSE.GPL
docs/LICENSE.txt
src/collective/__init__.py
src/collective.customoverrides.egg-info/PKG-INFO
src/collective.customoverrides.egg-info/SOURCES.txt
src/collective.customoverrides.egg-info/dependency_links.txt
src/collective.customoverrides.egg-info/entry_points.txt
src/collective.customoverrides.egg-info/namespace_packages.txt
src/collective.customoverrides.egg-info/not-zip-safe
src/collective.customoverrides.egg-info/paster_plugins.txt
src/collective.customoverrides.egg-info/requires.txt
src/collective.customoverrides.egg-info/top_level.txt
src/collective/customoverrides/__init__.py
src/collective/customoverrides/configure.zcml
src/collective/customoverrides/profiles.zcml
src/collective/customoverrides/testing.py
src/collective/customoverrides/upgrades.py
src/collective/customoverrides/browser/__init__.py
src/collective/customoverrides/browser/configure.zcml
src/collective/customoverrides/browser/interfaces.py
src/collective/customoverrides/browser/javascript.pt
src/collective/customoverrides/browser/style.pt
src/collective/customoverrides/profiles/default/metadata.xml
src/collective/customoverrides/profiles/default/viewlets.xml
src/collective/customoverrides/tests/__init__.py
src/collective/customoverrides/tests/robot_test.txt
src/collective/customoverrides/tests/test_example.py
src/collective/customoverrides/tests/test_robot.py