Metadata-Version: 1.0
Name: collective.customoverrides
Version: 1.0.1
Summary: Custom CSS and Javascript in Plone
Home-page: https://github.com/collective/collective.customoverrides
Author: Goldmund, Wyldebeast & Wunderliebe
Author-email: developers@gw20e.com
License: gpl
Platform: UNKNOWN
Classifier: Environment :: Web Environment
Classifier: Framework :: Plone
Classifier: Operating System :: OS Independent
Classifier: Programming Language :: Python
Classifier: Programming Language :: Python :: 2.6
Classifier: Topic :: Software Development :: Libraries :: Python Modules
